keyrock_fastapi/__init__.py
keyrock_fastapi/auth/__init__.py
keyrock_fastapi/auth/api_key.py
keyrock_fastapi/jwt/__init__.py
keyrock_fastapi/jwt/jwt.py
keyrock_fastapi/route/__init__.py
keyrock_fastapi/route/standard_response_route.py
keyrock_fastapi-2024.2.15.1117.dist-info/METADATA
keyrock_fastapi-2024.2.15.1117.dist-info/WHEEL
keyrock_fastapi-2024.2.15.1117.dist-info/top_level.txt
keyrock_fastapi-2024.2.15.1117.dist-info/RECORD
